[{"id": "125833793", "name": "Morral en lona para hombre Selene", "store": "V\u00e9lez", "price": 189900.0, "image": "https://cuerosvelezco.vteximg.com.br/arquivos/ids/299682/1039972-00-01-Morral.jpg?v=639002024498530000", "url": "https://www.velez.com.co/morral-1039972-00/p"}, {"id": "125833790", "name": "Morral en lona para mujer Sienna", "store": "V\u00e9lez", "price": 174930.0, "image": "https://cuerosvelezco.vteximg.com.br/arquivos/ids/300048/1039960-00-01-Morral.jpg?v=639014279803500000", "url": "https://www.velez.com.co/morral-1039960-00/p"}, {"id": "125833409", "name": "Tenis Spirited 2 para mujer Fly Up", "store": "V\u00e9lez", "price": 399900.0, "image": "https://cuerosvelezco.vteximg.com.br/arquivos/ids/296756/1039704-00-01-Tenis-deportivos.jpg?v=638930443477000000", "url": "https://www.velez.com.co/tenis-1039704-00/p"}, {"id": "125831676", "name": "Tenis Freedom 2.0 tejidos para hombre Fly Up", "store": "V\u00e9lez", "price": 314930.0, "image": "https://cuerosvelezco.vteximg.com.br/arquivos/ids/288249/1038864-00-01-Tenis-deportivos.jpg?v=638757434251830000", "url": "https://www.velez.com.co/tenis-1038864-00/p"}, {"id": "5434", "name": "Tenis vuelos de cuero para hombre combinaci\u00f3n de texturas", "store": "V\u00e9lez", "price": 349900.0, "image": "https://cuerosvelezco.vteximg.com.br/arquivos/ids/254109/1032285-00-01-Tenis-de-cuero.jpg?v=638271911602330000", "url": "https://www.velez.com.co/tenis-1032285-00/p"}, {"id": "125833725", "name": "Mocasines de cuero grabado para mujer Zippa 2", "store": "V\u00e9lez", "price": 339900.0, "image": "https://cuerosvelezco.vteximg.com.br/arquivos/ids/298027/1039525-00-01-Mocasines-de-cuero.jpg?v=638961329588030000", "url": "https://www.velez.com.co/mocasines-1039525-00/p"}, {"id": "125833683", "name": "Bowling en lona y cuero para mujer N\u00e1car", "store": "V\u00e9lez", "price": 164950.0, "image": "https://cuerosvelezco.vteximg.com.br/arquivos/ids/299812/1039126-31-01-Bolso-bowling.jpg?v=639009686451530000", "url": "https://www.velez.com.co/bowling-1039126-31/p"}, {"id": "125833405", "name": "Tenis Spirited 2 para hombre Fly Up", "store": "V\u00e9lez", "price": 279930.0, "image": "https://cuerosvelezco.vteximg.com.br/arquivos/ids/298135/1039699-00-01-Tenis-deportivos.jpg?v=638961454010070000", "url": "https://www.velez.com.co/tenis-1039699-00/p"}, {"id": "125832953", "name": "Manos libres en lona y cuero para mujer Tabata", "store": "V\u00e9lez", "price": 188930.0, "image": "https://cuerosvelezco.vteximg.com.br/arquivos/ids/297401/1039735-19-01-Bolso-manos-libres.jpg?v=638944950324730000", "url": "https://www.velez.com.co/manos-libres-1039735-19/p"}, {"id": "125832941", "name": "Tenis de cuero con detalle grabado para mujer Tropical 2", "store": "V\u00e9lez", "price": 349900.0, "image": "https://cuerosvelezco.vteximg.com.br/arquivos/ids/302442/1039275-02-01.jpg?v=639059384422270000", "url": "https://www.velez.com.co/tenis-1039275-02/p"}, {"id": "125832787", "name": "Tula morral en lona y cuero para mujer Biel", "store": "V\u00e9lez", "price": 272930.0, "image": "https://cuerosvelezco.vteximg.com.br/arquivos/ids/294960/1039382-00-01-Morral.jpg?v=638899213524730000", "url": "https://www.velez.com.co/morral-1039382-00/p"}, {"id": "125832544", "name": "Manos libres en lona y cuero para mujer Square", "store": "V\u00e9lez", "price": 209930.0, "image": "https://cuerosvelezco.vteximg.com.br/arquivos/ids/296459/1039373-00-01-Bolso-manos-libres.jpg?v=638929569592530000", "url": "https://www.velez.com.co/manos-libres-1039373-00/p"}, {"id": "125832313", "name": "Tenis de cuero para hombre Ibisa", "store": "V\u00e9lez", "price": 409900.0, "image": "https://cuerosvelezco.vteximg.com.br/arquivos/ids/293063/1039806-00-01-Tenis-de-cuero.jpg?v=638836108621430000", "url": "https://www.velez.com.co/tenis-1039806-00/p"}, {"id": "125831690", "name": "Tenis Freedom 2 para mujer Fly Up", "store": "V\u00e9lez", "price": 449900.0, "image": "https://cuerosvelezco.vteximg.com.br/arquivos/ids/288609/1038863-00-01-Tenis-deportivos.jpg?v=638760916225630000", "url": "https://www.velez.com.co/tenis-1038863-00/p"}, {"id": "125831087", "name": "Cintur\u00f3n unifaz Pradera de cuero para mujer grabado", "store": "V\u00e9lez", "price": 109900.0, "image": "https://cuerosvelezco.vteximg.com.br/arquivos/ids/286129/1038349-00-01-Cinturon-unifaz-de-cuero.jpg?v=638735834453000000", "url": "https://www.velez.com.co/cinturon-unifaz-1038349-00/p"}, {"id": "125831024", "name": "Morral Tamar en lona para mujer multifuncional", "store": "V\u00e9lez", "price": 272930.0, "image": "https://cuerosvelezco.vteximg.com.br/arquivos/ids/286720/1038774-00-01-Morral.jpg?v=638739475324430000", "url": "https://www.velez.com.co/morral-1038774-00/p"}, {"id": "125829985", "name": "Morral Sierra en lona para hombre manija cuero", "store": "V\u00e9lez", "price": 309900.0, "image": "https://cuerosvelezco.vteximg.com.br/arquivos/ids/279261/1037841-00-01-Morral.jpg?v=638585741146000000", "url": "https://www.velez.com.co/morral-1037841-00/p"}, {"id": "125829771", "name": "Morral Marfilo de cuero y nylon para mujer manija trenzada", "store": "V\u00e9lez", "price": 499900.0, "image": "https://cuerosvelezco.vteximg.com.br/arquivos/ids/290795/1037609-00-01-Morral.jpg?v=638803384700730000", "url": "https://www.velez.com.co/morral-1037609-00/p"}, {"id": "2481", "name": "Cintur\u00f3n unifaz de cuero liso", "store": "V\u00e9lez", "price": 89900.0, "image": "https://cuerosvelezco.vteximg.com.br/arquivos/ids/191089/1029743-02-01-cinturon-unifaz-de-cuero.jpg?v=637413475132070000", "url": "https://www.velez.com.co/cinturon-unifaz-1029743-02/p"}, {"id": "250", "name": "Morral Legacy de Nylon monocrom\u00e1tico Negro", "store": "V\u00e9lez", "price": 609900.0, "image": "https://cuerosvelezco.vteximg.com.br/arquivos/ids/235292/1021830-00-01-Morral-de-cuero.jpg?v=637897706441400000", "url": "https://www.velez.com.co/morral-1021830-00/p"}, {"id": "125836010", "name": "Tenis en gamuza para mujer Marina", "store": "V\u00e9lez", "price": 499900.0, "image": "https://cuerosvelezco.vteximg.com.br/arquivos/ids/301323/1040397-32-01-Tenis-de-cuero.jpg?v=639044319119000000", "url": "https://www.velez.com.co/tenis-1040397-32/p"}, {"id": "125835195", "name": "Camisetas semi fitted Monaco para hombre", "store": "V\u00e9lez", "price": 223930.0, "image": "https://cuerosvelezco.vteximg.com.br/arquivos/ids/301448/1040615-20-01-Camisetas.jpg?v=639045328026830000", "url": "https://www.velez.com.co/kit-1040615-20/p"}, {"id": "125834258", "name": "Cintur\u00f3n Asiri doble faz en cuero para hombre", "store": "V\u00e9lez", "price": 129900.0, "image": "https://cuerosvelezco.vteximg.com.br/arquivos/ids/299993/1039603-10-01-Cinturon-doble-faz-de-cuero.jpg?v=639014231312400000", "url": "https://www.velez.com.co/cinturon-doble-faz-1039603-10/p"}, {"id": "125834058", "name": "Morral P\u00farpura en lona para mujer casual", "store": "V\u00e9lez", "price": 184950.0, "image": "https://cuerosvelezco.vteximg.com.br/arquivos/ids/301195/1038943-14-01-Morral.jpg?v=639041693079300000", "url": "https://www.velez.com.co/morral-1038943-14/p"}, {"id": "125834047", "name": "Tenis Freedom 2 para mujer Fly Up", "store": "V\u00e9lez", "price": 449900.0, "image": "https://cuerosvelezco.vteximg.com.br/arquivos/ids/298396/1038863-09-01-Tenis-deportivos.jpg?v=638967476001600000", "url": "https://www.velez.com.co/tenis-1038863-09/p"}, {"id": "125834029", "name": "Morral Tamar en lona para mujer multifuncional", "store": "V\u00e9lez", "price": 272930.0, "image": "https://cuerosvelezco.vteximg.com.br/arquivos/ids/304757/1038774-19-01-Morral.jpg?v=639094580887270000", "url": "https://www.velez.com.co/morral-1038774-19/p"}, {"id": "125833726", "name": "Mocasines de cuero grabado para mujer Zippa 2", "store": "V\u00e9lez", "price": 339900.0, "image": "https://cuerosvelezco.vteximg.com.br/arquivos/ids/298032/1039525-02-01-Mocasines-de-cuero.jpg?v=638961331068330000", "url": "https://www.velez.com.co/mocasines-1039525-02/p"}, {"id": "125833411", "name": "Tenis Spirited 2 para mujer Fly Up", "store": "V\u00e9lez", "price": 399900.0, "image": "https://cuerosvelezco.vteximg.com.br/arquivos/ids/301235/1039704-09-01-Tenis-deportivos.jpg?v=639041880738300000", "url": "https://www.velez.com.co/tenis-1039704-09/p"}, {"id": "125833008", "name": "Bowling Dynamik para mujer Fly Up", "store": "V\u00e9lez", "price": 149950.0, "image": "https://cuerosvelezco.vteximg.com.br/arquivos/ids/295241/1039728-00-01-Bolso-bowling.jpg?v=638902649738070000", "url": "https://www.velez.com.co/bowling-1039728-00/p"}, {"id": "125832952", "name": "Manos libres en lona y cuero para mujer Tabata", "store": "V\u00e9lez", "price": 188930.0, "image": "https://cuerosvelezco.vteximg.com.br/arquivos/ids/297396/1039735-09-01-Bolso-manos-libres.jpg?v=638944949595470000", "url": "https://www.velez.com.co/manos-libres-1039735-09/p"}, {"id": "125832942", "name": "Tenis de cuero con detalle grabado para mujer Tropical 2", "store": "V\u00e9lez", "price": 349900.0, "image": "https://cuerosvelezco.vteximg.com.br/arquivos/ids/301367/1039275-04-01-Tenis-de-cuero.jpg?v=639045297648630000", "url": "https://www.velez.com.co/tenis-1039275-04/p"}, {"id": "125832793", "name": "Manos libres en lona y cuero para mujer Camelia", "store": "V\u00e9lez", "price": 299900.0, "image": "https://cuerosvelezco.vteximg.com.br/arquivos/ids/301372/1039414-00-01-Bolso-manos-libres.jpg?v=639045300528470000", "url": "https://www.velez.com.co/manos-libres-1039414-00/p"}, {"id": "125832612", "name": "Billetera de cuero grabado para mujer Hiedra", "store": "V\u00e9lez", "price": 169900.0, "image": "https://cuerosvelezco.vteximg.com.br/arquivos/ids/295460/1039071-25-01-Billetera-de-cuero.jpg?v=638907787948430000", "url": "https://www.velez.com.co/billetera-1039071-25/p"}, {"id": "125832447", "name": "Morral P\u00farpura en lona para mujer casual", "store": "V\u00e9lez", "price": 258930.0, "image": "https://cuerosvelezco.vteximg.com.br/arquivos/ids/296384/1038943-00-01-Morral.jpg?v=638926187502300000", "url": "https://www.velez.com.co/morral-1038943-00/p"}, {"id": "125832315", "name": "Tenis de cuero para hombre Ibisa", "store": "V\u00e9lez", "price": 409900.0, "image": "https://cuerosvelezco.vteximg.com.br/arquivos/ids/293572/1039806-11-01-Tenis-de-cuero.jpg?v=638854217426770000", "url": "https://www.velez.com.co/tenis-1039806-11/p"}, {"id": "125832314", "name": "Tenis de cuero para hombre Ibisa", "store": "V\u00e9lez", "price": 409900.0, "image": "https://cuerosvelezco.vteximg.com.br/arquivos/ids/304268/1039806-02-01-Tenis-de-cuero.jpg?v=639088347197300000", "url": "https://www.velez.com.co/tenis-1039806-02/p"}, {"id": "125832251", "name": "Cintur\u00f3n unifaz de cuero para hombre Hazel", "store": "V\u00e9lez", "price": 119900.0, "image": "https://cuerosvelezco.vteximg.com.br/arquivos/ids/291764/1038639-00-01-Cinturon-unifaz-de-cuero.jpg?v=638823182389300000", "url": "https://www.velez.com.co/cinturon-unifaz-1038639-00/p"}, {"id": "125832216", "name": "Morral en lona para hombre Ledger", "store": "V\u00e9lez", "price": 369900.0, "image": "https://cuerosvelezco.vteximg.com.br/arquivos/ids/293680/1039295-00-01-Morral.jpg?v=638856820865330000", "url": "https://www.velez.com.co/morral-1039295-00/p"}, {"id": "125832189", "name": "Morral en lona para hombre Jackson", "store": "V\u00e9lez", "price": 299900.0, "image": "https://cuerosvelezco.vteximg.com.br/arquivos/ids/293642/1039143-00-01-Morral.jpg?v=638854373500100000", "url": "https://www.velez.com.co/morral-1039143-00/p"}, {"id": "125832148", "name": "Billetera de cuero para hombre Sienna", "store": "V\u00e9lez", "price": 139900.0, "image": "https://cuerosvelezco.vteximg.com.br/arquivos/ids/291400/1038664-00-01-Billetera-de-cuero.jpg?v=638815533051300000", "url": "https://www.velez.com.co/billetera-1038664-00/p"}, {"id": "125831677", "name": "Tenis Freedom 2.0 tejidos para hombre Fly Up", "store": "V\u00e9lez", "price": 224950.0, "image": "https://cuerosvelezco.vteximg.com.br/arquivos/ids/287758/1038864-07-01-Tenis-deportivos.jpg?v=638750528008930000", "url": "https://www.velez.com.co/tenis-1038864-07/p"}, {"id": "125831271", "name": "Morral Avery en lona para hombre vers\u00e1til", "store": "V\u00e9lez", "price": 329900.0, "image": "https://cuerosvelezco.vteximg.com.br/arquivos/ids/285072/1038763-00-01-Morral.jpg?v=638699628981730000", "url": "https://www.velez.com.co/morral-1038763-00/p"}, {"id": "125831027", "name": "Morral Broni de lona para mujer vers\u00e1til", "store": "V\u00e9lez", "price": 272930.0, "image": "https://cuerosvelezco.vteximg.com.br/arquivos/ids/290401/1038775-00-01-Morral.jpg?v=638796390068230000", "url": "https://www.velez.com.co/morral-1038775-00/p"}, {"id": "125831026", "name": "Morral Tamar en lona para mujer multifuncional", "store": "V\u00e9lez", "price": 272930.0, "image": "https://cuerosvelezco.vteximg.com.br/arquivos/ids/293124/1038774-31-01-Morral.jpg?v=638839738905400000", "url": "https://www.velez.com.co/morral-1038774-31/p"}, {"id": "125830931", "name": "Cintur\u00f3n doble faz Calix de cuero para mujer monogram", "store": "V\u00e9lez", "price": 119900.0, "image": "https://cuerosvelezco.vteximg.com.br/arquivos/ids/292633/1038462-09-01-Cinturon-doble-faz-de-cuero.jpg?v=638833736068800000", "url": "https://www.velez.com.co/cinturon-doble-faz-1038462-09/p"}, {"id": "125829991", "name": "Tula morral Kaiser de lona y cuero para hombre estilo urbano", "store": "V\u00e9lez", "price": 369900.0, "image": "https://cuerosvelezco.vteximg.com.br/arquivos/ids/279271/1037843-00-01-Morral.jpg?v=638585744616800000", "url": "https://www.velez.com.co/morral-1037843-00/p"}, {"id": "125829772", "name": "Morral Marfilo de cuero y nylon para mujer manija trenzada", "store": "V\u00e9lez", "price": 299940.0, "image": "https://cuerosvelezco.vteximg.com.br/arquivos/ids/280123/1037609-02-01-Morral.jpg?v=638591720264930000", "url": "https://www.velez.com.co/morral-1037609-02/p"}, {"id": "125828601", "name": "Morral saba de cuero para mujer bolsillo frontal grabado", "store": "V\u00e9lez", "price": 503930.0, "image": "https://cuerosvelezco.vteximg.com.br/arquivos/ids/276028/1035506-02-01-Morral-de-cuero.jpg?v=638507992687700000", "url": "https://www.velez.com.co/morral-1035506-02/p"}, {"id": "125828600", "name": "Morral saba de cuero para mujer bolsillo frontal grabado", "store": "V\u00e9lez", "price": 503930.0, "image": "https://cuerosvelezco.vteximg.com.br/arquivos/ids/276023/1035506-00-01-Morral-de-cuero.jpg?v=638507992174830000", "url": "https://www.velez.com.co/morral-1035506-00/p"}, {"id": "125828516", "name": "Tula morral oasis de lona para hombre detalle acento de color", "store": "V\u00e9lez", "price": 509900.0, "image": "https://cuerosvelezco.vteximg.com.br/arquivos/ids/278271/1037128-58-01-Morral.jpg?v=638560646096430000", "url": "https://www.velez.com.co/morral-1037128-58/p"}, {"id": "10136652", "name": "Polo B\u00e1sica para Hombre Algod\u00f3n Con Ajuste El\u00e1stico", "store": "Arturo Calle", "price": 74990.0, "image": "https://arturocalle.vteximg.com.br/arquivos/ids/809762/HOMBRE-POLO-10136652-AZUL-799_1.jpg?v=639105716472600000", "url": "https://www.arturocalle.com/polo-unicolor-basica-para-hombre-36652-1/p"}, {"id": "403111", "name": "Bono de Regalo Virtual $100.000", "store": "Arturo Calle", "price": 100000.0, "image": "https://arturocalle.vteximg.com.br/arquivos/ids/631875/Bono_100-AC.jpg?v=638518122168600000", "url": "https://www.arturocalle.com/bono-de-regalo-virtual-arturo-calle-403111/p"}, {"id": "101484351", "name": "Polo Unicolor para Hombre 48435", "store": "Arturo Calle", "price": 74990.0, "image": "https://arturocalle.vteximg.com.br/arquivos/ids/803625/HOMBRE-POLO-10148435-ARENA-300_1.jpg?v=638991591415200000", "url": "https://www.arturocalle.com/polo-unicolor-para-hombre-484351/p"}, {"id": "101043613", "name": "Bermuda para Hombre Regular Fit de Tiro Alto y Silueta Recta Combinada", "store": "Arturo Calle", "price": 129990.0, "image": "https://arturocalle.vteximg.com.br/arquivos/ids/873587/HOMBRE-BERMUDA-10104361-HABANO-340_1.jpg?v=639111824730400000", "url": "https://www.arturocalle.com/bermuda-unicolor-regular-fit-para-hombre-101043613/p"}, {"id": "10129846", "name": "Camiseta para Hombre Regular Fit Cuello Redondo en Algod\u00f3n Jersey", "store": "Arturo Calle", "price": 49990.0, "image": "https://arturocalle.vteximg.com.br/arquivos/ids/823827/HOMBRE-CAMISETA-10129846-AZUL-790_1.jpg?v=639014324623000000", "url": "https://www.arturocalle.com/camiseta-basica-para-hombre-29846-1/p"}, {"id": "10125938", "name": "Polo Premium para Hombre Algod\u00f3n de Punto", "store": "Arturo Calle", "price": 94990.0, "image": "https://arturocalle.vteximg.com.br/arquivos/ids/803149/HOMBRE-POLO-10125938-BLANCO-000_1.jpg?v=638987517925000000", "url": "https://www.arturocalle.com/polo-premium-slim-fit-para-hombre--10125938/p"}, {"id": "403113", "name": "Bono de Regalo Virtual $200.000", "store": "Arturo Calle", "price": 200000.0, "image": "https://arturocalle.vteximg.com.br/arquivos/ids/631877/Bono_200-AC.jpg?v=638518122877270000", "url": "https://www.arturocalle.com/bono-de-regalo-virtual-arturo-calle-403113/p"}, {"id": "403112", "name": "Bono de Regalo Virtual $150.000", "store": "Arturo Calle", "price": 150000.0, "image": "https://arturocalle.vteximg.com.br/arquivos/ids/631876/Bono_150-AC.jpg?v=638518122525500000", "url": "https://www.arturocalle.com/bono-de-regalo-virtual-arturo-calle-403112/p"}, {"id": "101324511", "name": "Pantal\u00f3n para Hombre Regular Fit Tiro Medio y Bota Recta en Algod\u00f3n", "store": "Arturo Calle", "price": 189990.0, "image": "https://arturocalle.vteximg.com.br/arquivos/ids/883057/10132451037-1-1.jpg?v=639124930550770000", "url": "https://www.arturocalle.com/pantalon-casual-wf-unicolor-regular-fit-para-hombre-324511-1/p"}, {"id": "10151780", "name": "Polo Unicolor Premium para Hombre en Algodon Tejido Punto Interlock", "store": "Arturo Calle", "price": 94990.0, "image": "https://arturocalle.vteximg.com.br/arquivos/ids/872079/HOMBRE-POLO-10151780-AZUL-730_1.jpg?v=639111256906800000", "url": "https://www.arturocalle.com/polo-unicolor-premium-para-hombre-en-algodon-tejido-punto-interlock/p"}, {"id": "10151776", "name": "Polo Unicolor para Hombre en Cuello Tejido", "store": "Arturo Calle", "price": 74990.0, "image": "https://arturocalle.vteximg.com.br/arquivos/ids/883612/HOMBRE-POLO-10151776-AZUL-750_1.jpg?v=639125829261470000", "url": "https://www.arturocalle.com/polo-unicolor-para-hombre-en-cuello-tejido/p"}, {"id": "10148442", "name": "Camiseta Unicolor para Hombre Cuello Redondo en Algod\u00f3n Calidad Superior", "store": "Arturo Calle", "price": 49990.0, "image": "https://arturocalle.vteximg.com.br/arquivos/ids/801747/HOMBRE-CAMISETA-10148442-AZUL-770_1.jpg?v=638985844081670000", "url": "https://www.arturocalle.com/camiseta-unicolor-cuello-redondo-para-hombre-48442-1/p"}, {"id": "10148438", "name": "Polo para Hombre Algod\u00f3n con Ajuste El\u00e1stico", "store": "Arturo Calle", "price": 74990.0, "image": "https://arturocalle.vteximg.com.br/arquivos/ids/849343/HOMBRE-POLO-10148438-ROSADO-599_1.jpg?v=639111640958670000", "url": "https://www.arturocalle.com/polo-unicolor-para-hombre-48438-1/p"}, {"id": "10136651", "name": "Polo B\u00e1sica para Hombre Algod\u00f3n Tejido Piqu\u00e9", "store": "Arturo Calle", "price": 74990.0, "image": "https://arturocalle.vteximg.com.br/arquivos/ids/803227/HOMBRE-POLO-10136651-AZUL-799_1.jpg?v=638990938074830000", "url": "https://www.arturocalle.com/polo-unicolor-regular-fit-para-hombre-36651-1/p"}, {"id": "10136649", "name": "Polo B\u00e1sica para Hombre Algod\u00f3n", "store": "Arturo Calle", "price": 74990.0, "image": "https://arturocalle.vteximg.com.br/arquivos/ids/803185/HOMBRE-POLO-10136649-AZUL-799_1--1-.jpg?v=638992677043330000", "url": "https://www.arturocalle.com/polo-unicolor-regular-fit-para-hombre-36649-1/p"}, {"id": "10135115", "name": "Medias Formales para Hombre Algod\u00f3n y Poli\u00e9ster", "store": "Arturo Calle", "price": 13900.0, "image": "https://arturocalle.vteximg.com.br/arquivos/ids/706490/HOMBRE-MEDIAS-10135115-AZUL-790_1.jpg?v=638785232226230000", "url": "https://www.arturocalle.com/medias-formales-con-diseno-para-hombre-35115-1/p"}, {"id": "10134964", "name": "Perfume Green para Hombre", "store": "Arturo Calle", "price": 99990.0, "image": "https://arturocalle.vteximg.com.br/arquivos/ids/656364/HOMBRE-PERFUME-10134964-VARIOS-2.jpg?v=638702157478930000", "url": "https://www.arturocalle.com/perfume-green-arturo-calle-34964-1/p"}, {"id": "10132397", "name": "Suecos para Hombre Material Sint\u00e9tico", "store": "Arturo Calle", "price": 134900.0, "image": "https://arturocalle.vteximg.com.br/arquivos/ids/800939/HOMBRE-ZAPATOS-10132397-NEGRO-090_1.jpg?v=638984855820200000", "url": "https://www.arturocalle.com/zuecos-para-hombre-32397-1/p"}, {"id": "10125996", "name": "Camiseta Unicolor para Hombre Regular Fit Cuello Redondo en Algod\u00f3n", "store": "Arturo Calle", "price": 64990.0, "image": "https://arturocalle.vteximg.com.br/arquivos/ids/823897/HOMBRE-CAMISETA-10125996-BLANCO-000_1.jpg?v=639015148116200000", "url": "https://www.arturocalle.com/camiseta-basica-regular-fit-para-hombre-25996-1/p"}, {"id": "10125937", "name": "Polo Premium B\u00e1sica para Hombre Algod\u00f3n", "store": "Arturo Calle", "price": 94990.0, "image": "https://arturocalle.vteximg.com.br/arquivos/ids/802993/HOMBRE-POLO-10125937-AZUL-780_1.jpg?v=639111634382100000", "url": "https://www.arturocalle.com/polo-premium-regular-fit-para-hombre--10125937/p"}, {"id": "10120015", "name": "Sueter para Hombre Cuello Redondo en Tencel", "store": "Arturo Calle", "price": 119900.0, "image": "https://arturocalle.vteximg.com.br/arquivos/ids/831138/HOMBRE-SUETER-10120015-GRIS-070_1.jpg?v=639023822480300000", "url": "https://www.arturocalle.com/sueter-cuello-redondo-unicolor-para-hombre--10120015/p"}, {"id": "10091118", "name": "Perfume Blue para Hombre", "store": "Arturo Calle", "price": 99990.0, "image": "https://arturocalle.vteximg.com.br/arquivos/ids/531777/HOMBRE-LOCION-10091118-VARIOS--1.jpg?v=638702159740230000", "url": "https://www.arturocalle.com/perfume-blue-arturo-calle-10091118/p"}, {"id": "10091117", "name": "Perfume Black para Hombre", "store": "Arturo Calle", "price": 99990.0, "image": "https://arturocalle.vteximg.com.br/arquivos/ids/531781/HOMBRE-LOCION-10091117-VARIOS_1.jpg?v=638112961448730000", "url": "https://www.arturocalle.com/perfume-black-arturo-calle-10091117/p"}, {"id": "404351", "name": "Bono de Regalo Virtual $300.000", "store": "Arturo Calle", "price": 300000.0, "image": "https://arturocalle.vteximg.com.br/arquivos/ids/631878/Bono_300-AC.jpg?v=638518123477700000", "url": "https://www.arturocalle.com/bono-de-regalo-virtual-arturo-calle-404351/p"}, {"id": "403110", "name": "Bono de Regalo Virtual $50.000", "store": "Arturo Calle", "price": 50000.0, "image": "https://arturocalle.vteximg.com.br/arquivos/ids/631874/Bono_50-AC.jpg?v=638518091699970000", "url": "https://www.arturocalle.com/bono-de-regalo-virtual-arturo-calle-403110/p"}, {"id": "300141621", "name": "Polo Unicolor para Ni\u00f1o 14162", "store": "Arturo Calle", "price": 64900.0, "image": "https://arturocalle.vteximg.com.br/arquivos/ids/649660/NINO-POLO-30014162-AZUL-730_1.jpg?v=638558015076070000", "url": "https://www.arturocalle.com/polo-unicolor-para-nino-141621/p"}, {"id": "30015989", "name": "Tenis para Ni\u00f1o 15989", "store": "Arturo Calle", "price": 129900.0, "image": "https://arturocalle.vteximg.com.br/arquivos/ids/839494/NINO-TENIS-30015989-NEGRO-090_1.jpg?v=639050637683430000", "url": "https://www.arturocalle.com/tenis-para-ni\u00f1o-15989-1/p"}, {"id": "30014698", "name": "Tenis para Ni\u00f1a 14698", "store": "Arturo Calle", "price": 84435.0, "image": "https://arturocalle.vteximg.com.br/arquivos/ids/782023/NINA-TENIS-30014698-ARENA-300_1.jpg?v=638926924874730000", "url": "https://www.arturocalle.com/tenis-para-nina-14698-1/p"}, {"id": "30014609", "name": "Tenis con Dise\u00f1o para Ni\u00f1a 14609", "store": "Arturo Calle", "price": 159900.0, "image": "https://arturocalle.vteximg.com.br/arquivos/ids/784750/NINA-TENIS-30014609-ARENA-300_1.jpg?v=638935676398900000", "url": "https://www.arturocalle.com/tenis-con-diseno-para-nina-14609/p"}, {"id": "10153350", "name": "Perfume Blue Arturo Calle 30ml", "store": "Arturo Calle", "price": 49900.0, "image": "https://arturocalle.vteximg.com.br/arquivos/ids/827438/HOMBRE-PERFUME-10153350-AZUL-730_1.jpg?v=639020338498230000", "url": "https://www.arturocalle.com/perfume-blue-arturo-calle-30ml/p"}, {"id": "10152477", "name": "Tenis para Hombre de Textura Suave en Cuero y EVA", "store": "Arturo Calle", "price": 289990.0, "image": "https://arturocalle.vteximg.com.br/arquivos/ids/830512/HOMBRE-TENIS-10152477-NEGRO-090_1.jpg?v=639023703711970000", "url": "https://www.arturocalle.com/tenis-para-hombre-52477/p"}, {"id": "10151781", "name": "Polo Unicolor Premium para Hombre Algod\u00f3n Interlock", "store": "Arturo Calle", "price": 94990.0, "image": "https://arturocalle.vteximg.com.br/arquivos/ids/872143/HOMBRE-POLO-10151781-VINO-490_1.jpg?v=639111256961200000", "url": "https://www.arturocalle.com/polo-unicolor-premium-para-hombre-en-algodon-interlock-1/p"}, {"id": "10151775", "name": "Camiseta Polo Unicolor para Hombre Cuello Tejido en Piqu\u00e9", "store": "Arturo Calle", "price": 74990.0, "image": "https://arturocalle.vteximg.com.br/arquivos/ids/881680/HOMBRE-POLO-10151775-AZUL-710_1.jpg?v=639123064052170000", "url": "https://www.arturocalle.com/camiseta-polo-unicolor-para-hombre-cuello-tejido-en-pique/p"}, {"id": "10151407", "name": "Maleta B\u00e1sica para Hombre 51407", "store": "Arturo Calle", "price": 239900.0, "image": "https://arturocalle.vteximg.com.br/arquivos/ids/847202/HOMBRE-MALETA-10151407-AZUL-790_1.jpg?v=639065287230700000", "url": "https://www.arturocalle.com/maleta-basica-para-hombre-51407-1/p"}, {"id": "10149222", "name": "Jean Para Hombre Slim Tiro Medio y Bota Justa", "store": "Arturo Calle", "price": 99900.0, "image": "https://arturocalle.vteximg.com.br/arquivos/ids/783283/HOMBRE-JEAN-10149222-AZUL-710_1.jpg?v=638932236784530000", "url": "https://www.arturocalle.com/jean-slim-para-hombre-49222-1/p"}, {"id": "10148457", "name": "Camiseta Unicolor para Hombre Cuello V en Algod\u00f3n Arturo Calle", "store": "Arturo Calle", "price": 49990.0, "image": "https://arturocalle.vteximg.com.br/arquivos/ids/824017/HOMBRE-CAMISETA-10148457-GRIS-040_1.jpg?v=639015841179730000", "url": "https://www.arturocalle.com/camiseta-algodon-con-cuello-v-para-hombre-48457-1/p"}, {"id": "10148119", "name": "Polo Unicolor para Hombre Algod\u00f3n Piqu\u00e9", "store": "Arturo Calle", "price": 74990.0, "image": "https://arturocalle.vteximg.com.br/arquivos/ids/805392/HOMBRE-POLO-10148119-NEGRO-090_1.jpg?v=638991788064930000", "url": "https://www.arturocalle.com/polo-unicolor-para-hombre-48119-1/p"}, {"id": "10146636", "name": "Jean Para Hombre Slim Tiro Medio y Bota Justa", "store": "Arturo Calle", "price": 99900.0, "image": "https://arturocalle.vteximg.com.br/arquivos/ids/774211/HOMBRE-JEAN-10146636-AZUL-740_1.jpg?v=639112510853270000", "url": "https://www.arturocalle.com/jean-denim-slim-para-hombre-46636-1/p"}, {"id": "10145981", "name": "Camisa Formal para Hombre Semi Slim Fit Cuello Angeles", "store": "Arturo Calle", "price": 109990.0, "image": "https://arturocalle.vteximg.com.br/arquivos/ids/824581/HOMBRE-CAMISA-10145981-BLANCO-000_1.jpg?v=639015995678070000", "url": "https://www.arturocalle.com/camisa-formal-para-hombre-45981-1/p"}, {"id": "10136650", "name": "Polo B\u00e1sica para Hombre Unicolor Algod\u00f3n", "store": "Arturo Calle", "price": 74990.0, "image": "https://arturocalle.vteximg.com.br/arquivos/ids/803165/HOMBRE-POLO-10136650-BLANCO-000_1.jpg?v=639111633315400000", "url": "https://www.arturocalle.com/polo-unicolor-slim-fit-para-hombre-36650-1/p"}, {"id": "10129845", "name": "Camiseta Unicolor para Hombre Regular Fit Cuello Redondo en Algod\u00f3n", "store": "Arturo Calle", "price": 49990.0, "image": "https://arturocalle.vteximg.com.br/arquivos/ids/823937/HOMBRE-CAMISETA-10129845-AZUL-790_1.jpg?v=639015151040970000", "url": "https://www.arturocalle.com/camiseta-basica-para-hombre-29845-1/p"}, {"id": "10127518", "name": "Perfume para Mujer Modern Flower 27518", "store": "Arturo Calle", "price": 89990.0, "image": "https://arturocalle.vteximg.com.br/arquivos/ids/491253/MUJER-PERFUME-10127518-VARIOS_1.jpg?v=638006844560400000", "url": "https://www.arturocalle.com/perfume-para-mujer-modern-flower--10127518/p"}, {"id": "10091119", "name": "Perfume Purple para Hombre", "store": "Arturo Calle", "price": 99990.0, "image": "https://arturocalle.vteximg.com.br/arquivos/ids/531784/HOMBRE-LOCION-10091119-VARIOS_1.jpg?v=638112962134100000", "url": "https://www.arturocalle.com/perfume-purple-arturo-calle-10091119/p"}, {"id": "10075404", "name": "Sombrilla Autom\u00e1tica Estilo Funcional con Estructura de Metal", "store": "Arturo Calle", "price": 74900.0, "image": "https://arturocalle.vteximg.com.br/arquivos/ids/261877/HOMBRE-SOMBRILLA-10075404-ROJO-440_1.jpg?v=637285685448830000", "url": "https://www.arturocalle.com/sombrilla-automatica-grande--10075404/p"}, {"id": "101527451", "name": "Polo para Mujer 52745", "store": "Arturo Calle", "price": 74990.0, "image": "https://arturocalle.vteximg.com.br/arquivos/ids/835685/MUJER-POLO-10152745-BLANCO-000_1.jpg?v=639035866857430000", "url": "https://www.arturocalle.com/polo-para-mujer-52745-2/p"}, {"id": "101484381", "name": "Polo Unicolor para Hombre 48438", "store": "Arturo Calle", "price": 74990.0, "image": "https://arturocalle.vteximg.com.br/arquivos/ids/810298/HOMBRE-POLO-10148438-ROJO-430_1.jpg?v=638994284999300000", "url": "https://www.arturocalle.com/polo-unicolor-para-hombre-484381/p"}, {"id": "101357391", "name": "Zuecos para Mujer 35739", "store": "Arturo Calle", "price": 134900.0, "image": "https://arturocalle.vteximg.com.br/arquivos/ids/591824/MUJER-ZAPATOS-10135739-LILA-600_1.jpg?v=638337784393100000", "url": "https://www.arturocalle.com/zuecos-para-mujer-357391/p"}, {"id": "30016233", "name": "Buzo para Ni\u00f1a 16233", "store": "Arturo Calle", "price": 59925.0, "image": "https://arturocalle.vteximg.com.br/arquivos/ids/847805/NINA-BUZO-30016233-ARENA-300_1.jpg?v=639065288001000000", "url": "https://www.arturocalle.com/buzo-para-ni\u00f1a-16233-1/p"}, {"id": "30016074", "name": "Tenis para Ni\u00f1o 16074", "store": "Arturo Calle", "price": 97425.0, "image": "https://arturocalle.vteximg.com.br/arquivos/ids/857377/NINO-TENIS-30016074-ARENA-300_1.jpg?v=639076477253530000", "url": "https://www.arturocalle.com/tenis-para-ni\u00f1o-16074-1/p"}, {"id": "30016073", "name": "Tenis para Ni\u00f1o 16073", "store": "Arturo Calle", "price": 97425.0, "image": "https://arturocalle.vteximg.com.br/arquivos/ids/841913/NINO-TENIS-30016073-VARIOS-000_1.jpg?v=639056395349400000", "url": "https://www.arturocalle.com/tenis-para-ni\u00f1o-16073-1/p"}, {"id": "8616783872153", "name": "Garden LS T-Shirt - Black", "store": "TRUE", "price": 285000.0, "image": "https://cdn.shopify.com/s/files/1/0311/9398/9260/files/Garden_LS_T-Shirt_Washed_Black_2.jpg?v=1775766429", "url": "https://trueshop.co/products/garden-ls-t-shirt-black"}, {"id": "8616783839385", "name": "Fantasy Golfer Cap - Washed Brown", "store": "TRUE", "price": 130000.0, "image": "https://cdn.shopify.com/s/files/1/0311/9398/9260/files/Fantasy-Golfer-Cap---Washed-Brown_1_4cac5d33-55e3-446d-8275-bf49965fd50f.jpg?v=1775764368", "url": "https://trueshop.co/products/fantasy-golfer-cap-washed-brown"}, {"id": "8616783806617", "name": "Garden T-Shirt - Gray", "store": "TRUE", "price": 260000.0, "image": "https://cdn.shopify.com/s/files/1/0311/9398/9260/files/Garden_T-Shirt_Gray_2.jpg?v=1775766649", "url": "https://trueshop.co/products/garden-t-shirt-gray"}, {"id": "8616783741081", "name": "Fantasy T-Shirt - Black", "store": "TRUE", "price": 260000.0, "image": "https://cdn.shopify.com/s/files/1/0311/9398/9260/files/Fantasy_T-Shirt_Black_1.jpg?v=1775765469", "url": "https://trueshop.co/products/fantasy-t-shirt-black"}, {"id": "8616783708313", "name": "True Classic Jogger - Pine Green", "store": "TRUE", "price": 340000.0, "image": "https://cdn.shopify.com/s/files/1/0311/9398/9260/files/True_Classics_Jogger_Pine_Green_1.jpg?v=1774888225", "url": "https://trueshop.co/products/true-classic-jogger-pine-green"}, {"id": "8616783610009", "name": "True Classic Hoodie - Pine Green", "store": "TRUE", "price": 370000.0, "image": "https://cdn.shopify.com/s/files/1/0311/9398/9260/files/True_Classic_Hoodie_Pine_Green_1_0a1c1b4e-5502-47f0-9491-165d427bbfe4.jpg?v=1774887689", "url": "https://trueshop.co/products/true-classic-hoodie-pine-green"}, {"id": "8598004433049", "name": "Garden Fantasy Bandana - Baby Blue", "store": "TRUE", "price": 85000.0, "image": "https://cdn.shopify.com/s/files/1/0311/9398/9260/files/Garden-Fantasy-Bandana---Baby-Blue_1.jpg?v=1775766749", "url": "https://trueshop.co/products/garden-fantasy-bandana-baby-blue"}, {"id": "8598004400281", "name": "Knit Resort Bermuda - Sand", "store": "TRUE", "price": 220000.0, "image": "https://cdn.shopify.com/s/files/1/0311/9398/9260/files/IMG-8472.jpg?v=1774591411", "url": "https://trueshop.co/products/knit-resort-bermuda-sand"}, {"id": "8579649044633", "name": "Garden Plaid Shirt - Cream", "store": "TRUE", "price": 370000.0, "image": "https://cdn.shopify.com/s/files/1/0311/9398/9260/files/Garden-Plaid-Shirt---Cream_2_43148344-47ff-492d-b123-09f64bc27562.jpg?v=1775767027", "url": "https://trueshop.co/products/garden-plaid-shirt-cream"}, {"id": "8579649011865", "name": "Garden Socks - White", "store": "TRUE", "price": 38000.0, "image": "https://cdn.shopify.com/s/files/1/0311/9398/9260/files/Garden-Socks---White_1.jpg?v=1775765982", "url": "https://trueshop.co/products/garden-socks-white"}, {"id": "8579648979097", "name": "Fantasy Socks - Baby Blue", "store": "TRUE", "price": 38000.0, "image": "https://cdn.shopify.com/s/files/1/0311/9398/9260/files/Fantasy-Socks---Baby-Blue_1_9e032aab-b088-435a-b4c6-ea2e6a89f1b1.jpg?v=1775764950", "url": "https://trueshop.co/products/fantasy-socks-baby-blue"}, {"id": "8579648946329", "name": "Fantasy Puffer Mini Bag - Black", "store": "TRUE", "price": 190000.0, "image": "https://cdn.shopify.com/s/files/1/0311/9398/9260/files/Fantasy-Puffer-Mini-Bag---Black_2_61f215f0-eec8-4807-9e51-469e0cb9b141.jpg?v=1770750746", "url": "https://trueshop.co/products/fantasy-puffer-mini-bag-black"}, {"id": "8579648913561", "name": "Fantasy Golfer Cap - Washed Pine Green", "store": "TRUE", "price": 130000.0, "image": "https://cdn.shopify.com/s/files/1/0311/9398/9260/files/Fantasy-Golfer-Cap---Washed-Pine-Green_1.jpg?v=1775764759", "url": "https://trueshop.co/products/fantasy-golfer-cap-washed-pine-green"}, {"id": "8579648848025", "name": "Garden LS T-Shirt - Washed Brown", "store": "TRUE", "price": 285000.0, "image": "https://cdn.shopify.com/s/files/1/0311/9398/9260/files/Garden_LS_T-Shirt_Washed_Brown_2.jpg?v=1775922226", "url": "https://trueshop.co/products/garden-ls-t-shirt-washed-brown"}, {"id": "8579648815257", "name": "Fantasy T-Shirt - Washed Cream", "store": "TRUE", "price": 260000.0, "image": "https://cdn.shopify.com/s/files/1/0311/9398/9260/files/Fantasy_T-Shirt_Washed_Cream_2.jpg?v=1775765741", "url": "https://trueshop.co/products/fantasy-t-shirt-washed-cream"}, {"id": "8579648782489", "name": "Garden T-Shirt - Deep Green", "store": "TRUE", "price": 260000.0, "image": "https://cdn.shopify.com/s/files/1/0311/9398/9260/files/Garden_T-Shirt_Deep_Green_1.jpg?v=1775922311", "url": "https://trueshop.co/products/garden-t-shirt-deep-green"}, {"id": "8579648749721", "name": "Garden Hoodie - Washed Pine Green", "store": "TRUE", "price": 490000.0, "image": "https://cdn.shopify.com/s/files/1/0311/9398/9260/files/Garden_Hoodie_Washed_Pine_Green_2.jpg?v=1775766226", "url": "https://trueshop.co/products/garden-hoodie-washed-pine-green"}, {"id": "8559449473177", "name": "Knit Resort Polo - Sand", "store": "TRUE", "price": 230000.0, "image": "https://cdn.shopify.com/s/files/1/0311/9398/9260/files/Knit-Resort-Polo---Sand_1.jpg?v=1774621264", "url": "https://trueshop.co/products/knit-resort-polo-sand"}, {"id": "8523763679385", "name": "True Cotton Boxer Shorts - Cream", "store": "TRUE", "price": 48000.0, "image": "https://cdn.shopify.com/s/files/1/0311/9398/9260/files/True_Cotton_Boxer_Shorts_Cream_1.jpg?v=1763753622", "url": "https://trueshop.co/products/true-cotton-boxer-shorts-cream"}, {"id": "8681484877977", "name": "La Solar x True Keychain - Orange", "store": "TRUE", "price": 25000.0, "image": "https://cdn.shopify.com/s/files/1/0311/9398/9260/files/La-Solar-x-True-Keychain---Orange_1.jpg?v=1777041336", "url": "https://trueshop.co/products/la-solar-x-true-keychain-orange"}, {"id": "8681484746905", "name": "La Solar x True Sun Cap - Cream", "store": "TRUE", "price": 80000.0, "image": "https://cdn.shopify.com/s/files/1/0311/9398/9260/files/La-Solar-X-True-Sun-Cap---White_1.jpg?v=1777041358", "url": "https://trueshop.co/products/la-solar-x-true-sun-cap-cream"}, {"id": "8681484714137", "name": "La Solar x True Socks - White", "store": "TRUE", "price": 30000.0, "image": "https://cdn.shopify.com/s/files/1/0311/9398/9260/files/LaSolarxTrueSocks-White_01.jpg?v=1777041378", "url": "https://trueshop.co/products/la-solar-x-true-socks-white"}, {"id": "8681484648601", "name": "La Solar x True Bandana - Black", "store": "TRUE", "price": 55000.0, "image": "https://cdn.shopify.com/s/files/1/0311/9398/9260/files/La-Solar-x-True-Bandana---Black_01.jpg?v=1777041637", "url": "https://trueshop.co/products/la-solar-x-true-bandana-black"}, {"id": "8681484615833", "name": "La Solar x True Sleeveless T-Shirt - Black", "store": "TRUE", "price": 140000.0, "image": "https://cdn.shopify.com/s/files/1/0311/9398/9260/files/La-Solar-X-True-Sleeveless-T-shirt---Black_1.jpg?v=1777041790", "url": "https://trueshop.co/products/la-solar-x-true-sleeveless-t-shirt-black"}, {"id": "8681484550297", "name": "La Solar x True LS T-Shirt - Cream", "store": "TRUE", "price": 210000.0, "image": "https://cdn.shopify.com/s/files/1/0311/9398/9260/files/La-Solar-x-True-LS-T-Shirt---Cream_02.jpg?v=1777041840", "url": "https://trueshop.co/products/la-solar-x-true-ls-t-shirt-cream"}, {"id": "8681484517529", "name": "La Solar x True Boxy T-Shirt - White", "store": "TRUE", "price": 170000.0, "image": "https://cdn.shopify.com/s/files/1/0311/9398/9260/files/La-Solar-X-True-Boxy-T-shirt---White_2_e004f0de-21cc-4caf-adaf-33c2b72de324.jpg?v=1777418832", "url": "https://trueshop.co/products/la-solar-x-true-boxy-t-shirt-white"}, {"id": "8559448752281", "name": "Short Sleeve Crewneck Bodysuit - Cream", "store": "TRUE", "price": 170000.0, "image": "https://cdn.shopify.com/s/files/1/0311/9398/9260/files/Short-Sleeve-Crewneck-Bodysuit---Cream_1_ef3f2f55-d5be-43dc-afd8-cd7912c14f6a.jpg?v=1772048566", "url": "https://trueshop.co/products/short-sleeve-crewneck-bodysuit-cream"}, {"id": "8491260412057", "name": "Everyday Logo Hoodie - Sky Blue", "store": "TRUE", "price": 280000.0, "image": "https://cdn.shopify.com/s/files/1/0311/9398/9260/files/Everyday_Logo_Hoodie-Sky_Blue_1.jpg?v=1762806892", "url": "https://trueshop.co/products/everyday-logo-hoodie-sky-blue"}, {"id": "8491260706969", "name": "Camo Fanny Pack - Green", "store": "TRUE", "price": 112000.0, "image": "https://cdn.shopify.com/s/files/1/0311/9398/9260/files/Camo_Fanny_Pack_Green_1.jpg?v=1761764518", "url": "https://trueshop.co/products/camo-fanny-pack-green"}, {"id": "8227414802585", "name": "Lucky Bandana - Cream", "store": "TRUE", "price": 64000.0, "image": "https://cdn.shopify.com/s/files/1/0311/9398/9260/files/The_Journey_Chess_Bandana_Cream_1.jpg?v=1738203984", "url": "https://trueshop.co/products/lucky-bandana-cream"}, {"id": "8227414737049", "name": "The Journey Bandana - Blue", "store": "TRUE", "price": 64000.0, "image": "https://cdn.shopify.com/s/files/1/0311/9398/9260/files/The_Journey_Bandana_Blue_1.jpg?v=1738203986", "url": "https://trueshop.co/products/the-journey-bandana-blue"}, {"id": "8559449505945", "name": "Pastel Fitted Tee - Butter Yellow", "store": "TRUE", "price": 110000.0, "image": "https://cdn.shopify.com/s/files/1/0311/9398/9260/files/Pastel-Fitted-Tee---Butter-Yellow_2_e6e9f33b-bf98-4d3f-ae5f-1617d0eadf36.jpg?v=1772484520", "url": "https://trueshop.co/products/pastel-fitted-tee-butter-yellow"}, {"id": "8460846465177", "name": "Chrome Long Sleeve Tee - Black/White", "store": "TRUE", "price": 290000.0, "image": "https://cdn.shopify.com/s/files/1/0311/9398/9260/files/Chrome-Long-Sleeve-Tee---BlackWhite_1.1.jpg?v=1764883978", "url": "https://trueshop.co/products/chrome-long-sleeve-tee-black-white"}, {"id": "8460846825625", "name": "Midnight Dust Sweatpants - Black", "store": "TRUE", "price": 370000.0, "image": "https://cdn.shopify.com/s/files/1/0311/9398/9260/files/Midnight-Dust-Sweatpants---Black_1.1.jpg?v=1764879969", "url": "https://trueshop.co/products/midnight-dust-sweatpants-black"}, {"id": "8415286460569", "name": "Colombia Bandana - Black", "store": "TRUE", "price": 80000.0, "image": "https://cdn.shopify.com/s/files/1/0311/9398/9260/files/Colombia-Bandana---Black-1.jpg?v=1748028188", "url": "https://trueshop.co/products/colombia-bandana-black"}, {"id": "8164976623769", "name": "Signature Crew Socks - Brown", "store": "TRUE", "price": 24500.0, "image": "https://cdn.shopify.com/s/files/1/0311/9398/9260/files/Signature_crew_Socks---Camel-1.jpg?v=1738204187", "url": "https://trueshop.co/products/signature-crew-socks-brown"}, {"id": "8164976492697", "name": "Signature Ribbed Top - White", "store": "TRUE", "price": 42500.0, "image": "https://cdn.shopify.com/s/files/1/0311/9398/9260/files/Signature-Ribbed-Top---White-5.jpg?v=1772142654", "url": "https://trueshop.co/products/signature-ribbed-top-white"}, {"id": "8529909809305", "name": "Fast Racing Bag - Black", "store": "TRUE", "price": 280000.0, "image": "https://cdn.shopify.com/s/files/1/0311/9398/9260/files/Fast-Racing-Bag---Black_1_1_38520a72-871d-4e75-ae16-68e75395b21d.jpg?v=1771261412", "url": "https://trueshop.co/products/fast-racing-bag-black"}, {"id": "8164976591001", "name": "Signature Socks - White", "store": "TRUE", "price": 35000.0, "image": "https://cdn.shopify.com/s/files/1/0311/9398/9260/files/Signature-Socks_White-1.jpg?v=1738204188", "url": "https://trueshop.co/products/signature-socks-white"}, {"id": "8304131997849", "name": "Pleated Mini Skirt - Khaki", "store": "TRUE", "price": 114000.0, "image": "https://cdn.shopify.com/s/files/1/0311/9398/9260/files/Pleated_Mini_Skirt_Khaki-1.jpg?v=1745542239", "url": "https://trueshop.co/products/pleated-mini-skirt-khaki"}, {"id": "8495257878681", "name": "Bubble Gum Belt - Pink", "store": "TRUE", "price": 120000.0, "image": "https://cdn.shopify.com/s/files/1/0311/9398/9260/files/Bubble-Gum-Belt---Pink_1.jpg?v=1764884181", "url": "https://trueshop.co/products/bubble-gum-belt-pink"}, {"id": "8559449538713", "name": "Pastel Fitted Tee - Baby Blue", "store": "TRUE", "price": 110000.0, "image": "https://cdn.shopify.com/s/files/1/0311/9398/9260/files/Pastel-Fitted-Tee---Baby-Blue_2_2edc075e-8545-4048-9269-203b1bca3fb4.jpg?v=1772484364", "url": "https://trueshop.co/products/pastel-fitted-tee-baby-blue"}, {"id": "8460846563481", "name": "Too Bright LS Bodysuit - Black", "store": "TRUE", "price": 190000.0, "image": "https://cdn.shopify.com/s/files/1/0311/9398/9260/files/Too-Bright-LS-Bodysuit---Black_1_29627b3f-30ff-47b4-8ab9-49992cc0b4dc.jpg?v=1765293315", "url": "https://trueshop.co/products/too-bright-ls-bodysuit-black"}, {"id": "8460846956697", "name": "Too Bright Golfer Cap - Yellow", "store": "TRUE", "price": 110000.0, "image": "https://cdn.shopify.com/s/files/1/0311/9398/9260/files/Too_Bright_Golfer_Cap_Yellow_1_75321ea1-863d-4226-9eac-da6e4b93ed3a.jpg?v=1762815922", "url": "https://trueshop.co/products/too-bright-golfer-cap-yellow"}, {"id": "8417468743833", "name": "Python Slim Cropped Tee - White", "store": "TRUE", "price": 69300.0, "image": "https://cdn.shopify.com/s/files/1/0311/9398/9260/files/DSC09262.jpg?v=1772142970", "url": "https://trueshop.co/products/python-slim-cropped-tee-white"}, {"id": "8517363892377", "name": "Textured Tank Top - Cream", "store": "TRUE", "price": 88000.0, "image": "https://cdn.shopify.com/s/files/1/0311/9398/9260/files/Textured-Tank-Top---Cream_2_1.jpg?v=1772141605", "url": "https://trueshop.co/products/textured-tank-top-cream"}, {"id": "8304132030617", "name": "Pleated Mini Skirt - Black", "store": "TRUE", "price": 114000.0, "image": "https://cdn.shopify.com/s/files/1/0311/9398/9260/files/Pleated_Mini_Skirt_Black-0.jpg?v=1746112451", "url": "https://trueshop.co/products/pleated-mini-skirt-black"}, {"id": "8292999856281", "name": "Caring Pareo - Brown", "store": "TRUE", "price": 60000.0, "image": "https://cdn.shopify.com/s/files/1/0311/9398/9260/files/Caring_Pareo_Brown-1.jpg?v=1751118559", "url": "https://trueshop.co/products/caring-pareo-brown"}, {"id": "8483688349849", "name": "True X Smirnoff Slim Tee - White", "store": "TRUE", "price": 59400.0, "image": "https://cdn.shopify.com/s/files/1/0311/9398/9260/files/True_X_Smirnoff_Slim_Tee_White_1.jpg?v=1772142918", "url": "https://trueshop.co/products/true-x-smirnoff-slim-tee-white"}, {"id": "8491260543129", "name": "Forest Zipper Hoodie - Green", "store": "TRUE", "price": 350000.0, "image": "https://cdn.shopify.com/s/files/1/0311/9398/9260/files/Forest_Zipper_Hoodie_2_79bb6a07-93b4-4457-9142-b3daec646d49.jpg?v=1761836576", "url": "https://trueshop.co/products/forest-zipper-hoodie-green"}, {"id": "hm_150", "name": "H&M Collection Item 1", "price": 120000.0, "store": "H&M", "image": "https://hmcolombia.vtexassets.com/assets/vtex.file-manager-graphql/images/65d86a72-63f8-4289-95e6-f24e21a3e703___e34ffadd5fcdedb1aef8def9201439f0.jpg", "url": "https://co.hm.com/"}, {"id": "hm_151", "name": "H&M Collection Item 2", "price": 130000.0, "store": "H&M", "image": "https://hmcolombia.vtexassets.com/assets/vtex.file-manager-graphql/images/758bed2c-da53-4442-bc6e-02d03c42e1bb___4738e4cfd21c0284205cb6670b16459d.jpg", "url": "https://co.hm.com/"}, {"id": "hm_152", "name": "H&M Collection Item 3", "price": 140000.0, "store": "H&M", "image": "https://hmcolombia.vtexassets.com/assets/vtex.file-manager-graphql/images/f143610b-ee8d-4e1f-b337-b21cbb5fd435___c7bdcdc21c36ec3950c0d79587ce7196.jpg", "url": "https://co.hm.com/"}, {"id": "hm_153", "name": "H&M Collection Item 4", "price": 150000.0, "store": "H&M", "image": "https://hmcolombia.vtexassets.com/assets/vtex.file-manager-graphql/images/cb9592c2-282f-46ac-b07d-0ba1306b9a2e___c7bdcdc21c36ec3950c0d79587ce7196.jpg", "url": "https://co.hm.com/"}, {"id": "hm_154", "name": "H&M Collection Item 5", "price": 160000.0, "store": "H&M", "image": "https://hmcolombia.vtexassets.com/assets/vtex.file-manager-graphql/images/48f3fe4c-0258-4639-a510-2c5cfc1aa85a___72e5b9d38c8fded9dac8664a22e0a6c7.jpg", "url": "https://co.hm.com/"}, {"id": "hm_155", "name": "H&M Collection Item 6", "price": 170000.0, "store": "H&M", "image": "https://hmcolombia.vtexassets.com/assets/vtex.file-manager-graphql/images/ac9b6292-744d-45ae-b86b-a67332d930ea___379d90a5d8d15c7122c4da7bcd51b932.jpg", "url": "https://co.hm.com/"}, {"id": "hm_156", "name": "H&M Collection Item 7", "price": 180000.0, "store": "H&M", "image": "https://hmcolombia.vtexassets.com/assets/vtex.file-manager-graphql/images/54ca85d2-f3f0-451e-9541-01e69a6826fe___a85b3a33553329d0b82116d48982f5e4.jpg", "url": "https://co.hm.com/"}, {"id": "hm_157", "name": "H&M Collection Item 8", "price": 190000.0, "store": "H&M", "image": "https://hmcolombia.vtexassets.com/assets/vtex.file-manager-graphql/images/a988bafa-8107-4d04-916e-bc0f0d3e9f6d___be98b1bb0e76e230db5629677818a672.jpg", "url": "https://co.hm.com/"}, {"id": "hm_158", "name": "H&M Collection Item 9", "price": 200000.0, "store": "H&M", "image": "https://hmcolombia.vtexassets.com/assets/vtex.file-manager-graphql/images/7ab3964e-0797-45a8-8196-901873572d6c___45a74fcfc09eb96c1083ff562aadbb4f.jpg", "url": "https://co.hm.com/"}, {"id": "hm_159", "name": "H&M Collection Item 10", "price": 210000.0, "store": "H&M", "image": "https://hmcolombia.vtexassets.com/assets/vtex.file-manager-graphql/images/e896d7eb-9f7b-49ec-9628-d46251f6b3a2___3eea22d50f76f777f3aafd5c3ab70f90.jpg", "url": "https://co.hm.com/"}, {"id": "hm_160", "name": "H&M Collection Item 11", "price": 220000.0, "store": "H&M", "image": "https://hmcolombia.vtexassets.com/assets/vtex.file-manager-graphql/images/99b787f6-1c8e-4c3a-8f63-678e0cfdce0a___00fd1bfe2424a45640850307b3bb4053.jpg", "url": "https://co.hm.com/"}, {"id": "hm_161", "name": "H&M Collection Item 12", "price": 230000.0, "store": "H&M", "image": "https://hmcolombia.vtexassets.com/assets/vtex.file-manager-graphql/images/bf209287-757d-4025-b64f-be4d6df4d4f7___e34ffadd5fcdedb1aef8def9201439f0.jpg", "url": "https://co.hm.com/"}, {"id": "hm_162", "name": "H&M Collection Item 13", "price": 240000.0, "store": "H&M", "image": "https://hmcolombia.vtexassets.com/assets/vtex.file-manager-graphql/images/1d4a45b6-390d-4711-95d1-f1341588ff21___cb8422943386dbb8f5f8666957a52b0b.jpg", "url": "https://co.hm.com/"}, {"id": "hm_163", "name": "H&M Collection Item 14", "price": 250000.0, "store": "H&M", "image": "https://hmcolombia.vtexassets.com/assets/vtex.file-manager-graphql/images/1296b1b3-e21d-4d46-9f93-022f263587de___a85b3a33553329d0b82116d48982f5e4.jpg", "url": "https://co.hm.com/"}, {"id": "hm_164", "name": "H&M Collection Item 15", "price": 260000.0, "store": "H&M", "image": "https://hmcolombia.vtexassets.com/assets/vtex.file-manager-graphql/images/acf3d7ce-a4ca-42e0-ae56-0bb723f35b78___e34ffadd5fcdedb1aef8def9201439f0.jpg", "url": "https://co.hm.com/"}, {"id": "hm_165", "name": "H&M Collection Item 16", "price": 270000.0, "store": "H&M", "image": "https://hmcolombia.vtexassets.com/assets/vtex.file-manager-graphql/images/5d11c662-a289-4b2b-8e6a-751a9d619d3f___c7bdcdc21c36ec3950c0d79587ce7196.jpg", "url": "https://co.hm.com/"}, {"id": "hm_166", "name": "H&M Collection Item 17", "price": 280000.0, "store": "H&M", "image": "https://hmcolombia.vtexassets.com/assets/vtex.file-manager-graphql/images/46429f74-8b92-4ad8-8ed5-e66cdd6184d3___a85b3a33553329d0b82116d48982f5e4.jpg", "url": "https://co.hm.com/"}, {"id": "hm_167", "name": "H&M Collection Item 18", "price": 290000.0, "store": "H&M", "image": "https://hmcolombia.vtexassets.com/assets/vtex.file-manager-graphql/images/83c8d478-67c9-4eac-8681-c4f01d5f2e17___50a46d9f9f4ac8456017dd3e9b752f4e.jpg", "url": "https://co.hm.com/"}, {"id": "hm_168", "name": "H&M Collection Item 19", "price": 300000.0, "store": "H&M", "image": "https://hmcolombia.vtexassets.com/assets/vtex.file-manager-graphql/images/3961616d-13d5-4dc3-b3f8-150915795a96___baf2d95a9c51159720930372a5c4e447.jpg", "url": "https://co.hm.com/"}, {"id": "hm_169", "name": "H&M Collection Item 20", "price": 310000.0, "store": "H&M", "image": "https://hmcolombia.vtexassets.com/assets/vtex.file-manager-graphql/images/862ec466-578f-43a0-ad36-f03165de05a0___7a3934b70631eb0aec6b0c784b5c071c.jpg", "url": "https://co.hm.com/"}]